Metadata-Version: 2.3
Name: pieces_os_client
Version: 4.4.1
Summary: A powerful code engine package for writing applications on top of PiecesOS
Home-page: https://pieces.app
License: MIT
Author: Pieces
Author-email: development@pieces.app
Requires-Python: >=3.8,<4.0
Classifier: License :: OSI Approved :: MIT License
Classifier: Programming Language :: Python :: 3
Classifier: Programming Language :: Python :: 3.8
Classifier: Programming Language :: Python :: 3.9
Classifier: Programming Language :: Python :: 3.10
Classifier: Programming Language :: Python :: 3.11
Classifier: Programming Language :: Python :: 3.12
Classifier: Programming Language :: Python :: 3.13
Requires-Dist: aenum (>=3.1.11)
Requires-Dist: pydantic (>=1.10.5,<2.0.0)
Requires-Dist: python-dateutil (>=2.8.2)
Requires-Dist: urllib3 (>=1.25.3)
Requires-Dist: websocket-client (>=1.8.0,<2.0.0)
Project-URL: Documentation, https://docs.pieces.app/build/reference/python/
Project-URL: Repository, https://github.com/pieces-app/pieces-os-client-sdk-for-python
Project-URL: issues, https://github.com/pieces-app/pieces-os-client-sdk-for-python/issues
